CHANGES.rst
COPYING.LGPLv3
MANIFEST.in
README.rst
setup.py
django_inplaceedit_extra_fields.egg-info/PKG-INFO
django_inplaceedit_extra_fields.egg-info/SOURCES.txt
django_inplaceedit_extra_fields.egg-info/dependency_links.txt
django_inplaceedit_extra_fields.egg-info/not-zip-safe
django_inplaceedit_extra_fields.egg-info/requires.txt
django_inplaceedit_extra_fields.egg-info/top_level.txt
inplaceeditform_extra_fields/__init__.py
inplaceeditform_extra_fields/adaptors.py
inplaceeditform_extra_fields/fields.py
inplaceeditform_extra_fields/widgets.py
inplaceeditform_extra_fields/static/adaptor_tiny/css/adaptor_tiny.css
inplaceeditform_extra_fields/templates/inplaceeditform_extra_fields/adaptor_autocomplete/inc.css_library.html
inplaceeditform_extra_fields/templates/inplaceeditform_extra_fields/adaptor_autocomplete/inc.js_library.html
inplaceeditform_extra_fields/templates/inplaceeditform_extra_fields/adaptor_autocomplete/render_js.html
inplaceeditform_extra_fields/templates/inplaceeditform_extra_fields/adaptor_autocomplete/render_media_field.html
inplaceeditform_extra_fields/templates/inplaceeditform_extra_fields/adaptor_autocomplete/render_value_edit.html
inplaceeditform_extra_fields/templates/inplaceeditform_extra_fields/adaptor_image_thumb/render_value.html
inplaceeditform_extra_fields/templates/inplaceeditform_extra_fields/adaptor_tiny/render_field.html
inplaceeditform_extra_fields/templates/inplaceeditform_extra_fields/adaptor_tiny/render_media_field.html
inplaceeditform_extra_fields/templates/inplaceeditform_extra_fields/adaptor_tiny/render_value_edit.html
inplaceeditform_extra_fields/templates/inplaceeditform_extra_fields/adaptor_tiny/setup.js