Metadata-Version: 1.1
Name: django-inplaceedit-extra-fields
Version: 0.6.0
Summary: Django application that adds other useful fields to Django inplace edit
Home-page: https://github.com/django-inplaceedit/django-inplaceedit-extra-fields
Author: Pablo Martin
Author-email: goinnn@gmail.com
License: LGPL 3
Keywords: django,inplace,inline edit,inline form,inline,inplace edit,inplace form,ajax,tinymce,autocomplete,thumbnail
Platform: UNKNOWN
Classifier: Development Status :: 4 - Beta
Classifier: Framework :: Django
Classifier: License :: OSI Approved :: GNU Library or Lesser General Public License (LGPL)
Classifier: Programming Language :: Python :: 2
Classifier: Programming Language :: Python :: 3
